mastakod_movies_sdk/__init__.py
mastakod_movies_sdk/film_client.py
mastakod_movies_sdk/film_config.py
mastakod_movies_sdk/schemas/__init__.py
mastakod_movies_sdk/schemas/schemas.py
mastakod_movies_sdk-0.0.1.dist-info/METADATA
mastakod_movies_sdk-0.0.1.dist-info/WHEEL
mastakod_movies_sdk-0.0.1.dist-info/top_level.txt
mastakod_movies_sdk-0.0.1.dist-info/RECORD
