Metadata-Version: 2.4
Name: mastakod_movies_sdk
Version: 0.0.1
Summary: Python Software Development Kit (SDK) for MovieLens API
Author: [Fred MAKITA]
Classifier: Development Status :: 3 - Alpha
Classifier: Programming Language :: Python :: 3
Classifier: License :: OSI Approved :: MIT License
Classifier: Operating System :: OS Independent
Requires-Python: >=3.13
Requires-Dist: httpx>=0.28.1
Requires-Dist: pydantic>=2.11.4
Requires-Dist: backoff>=2.2.1
Requires-Dist: python-dotenv
Requires-Dist: numpy>=2.2.4
Requires-Dist: pandas>=2.2.3
